azure/mgmt/appcomplianceautomation/__init__.py
azure/mgmt/appcomplianceautomation/_app_compliance_automation_mgmt_client.py
azure/mgmt/appcomplianceautomation/_configuration.py
azure/mgmt/appcomplianceautomation/_patch.py
azure/mgmt/appcomplianceautomation/_serialization.py
azure/mgmt/appcomplianceautomation/_vendor.py
azure/mgmt/appcomplianceautomation/_version.py
azure/mgmt/appcomplianceautomation/py.typed
azure/mgmt/appcomplianceautomation/aio/__init__.py
azure/mgmt/appcomplianceautomation/aio/_app_compliance_automation_mgmt_client.py
azure/mgmt/appcomplianceautomation/aio/_configuration.py
azure/mgmt/appcomplianceautomation/aio/_patch.py
azure/mgmt/appcomplianceautomation/aio/operations/__init__.py
azure/mgmt/appcomplianceautomation/aio/operations/_evidence_operations.py
azure/mgmt/appcomplianceautomation/aio/operations/_operations.py
azure/mgmt/appcomplianceautomation/aio/operations/_patch.py
azure/mgmt/appcomplianceautomation/aio/operations/_provider_actions_operations.py
azure/mgmt/appcomplianceautomation/aio/operations/_report_operations.py
azure/mgmt/appcomplianceautomation/aio/operations/_scoping_configuration_operations.py
azure/mgmt/appcomplianceautomation/aio/operations/_snapshot_operations.py
azure/mgmt/appcomplianceautomation/aio/operations/_webhook_operations.py
azure/mgmt/appcomplianceautomation/models/__init__.py
azure/mgmt/appcomplianceautomation/models/_app_compliance_automation_mgmt_client_enums.py
azure/mgmt/appcomplianceautomation/models/_models_py3.py
azure/mgmt/appcomplianceautomation/models/_patch.py
azure/mgmt/appcomplianceautomation/operations/__init__.py
azure/mgmt/appcomplianceautomation/operations/_evidence_operations.py
azure/mgmt/appcomplianceautomation/operations/_operations.py
azure/mgmt/appcomplianceautomation/operations/_patch.py
azure/mgmt/appcomplianceautomation/operations/_provider_actions_operations.py
azure/mgmt/appcomplianceautomation/operations/_report_operations.py
azure_mgmt_appcomplianceautomation-1.0.0.dist-info/LICENSE
azure_mgmt_appcomplianceautomation-1.0.0.dist-info/METADATA
azure_mgmt_appcomplianceautomation-1.0.0.dist-info/WHEEL
azure_mgmt_appcomplianceautomation-1.0.0.dist-info/top_level.txt
azure_mgmt_appcomplianceautomation-1.0.0.dist-info/RECORD
